webtree/__init__.py
webtree/app.py
webtree/main.py
webtree/template.py
webtree-0.0.17.dist-info/LICENSE.txt
webtree-0.0.17.dist-info/METADATA
webtree-0.0.17.dist-info/WHEEL
webtree-0.0.17.dist-info/entry_points.txt
webtree-0.0.17.dist-info/top_level.txt
webtree-0.0.17.dist-info/RECORD
