Metadata-Version: 2.1
Name: webtree
Version: 0.0.17
Summary: Displays HTML page as a Graph
Home-page: https://github.com/abishekshyamsunder/webtree
Author: Abishek Shyamsunder, Adithya Viswanathan
Author-email: abishekshyamsunder@gmail.com, adith_viswa@ymail.com
License: MIT license
Keywords: webtree
Platform: UNKNOWN
Classifier: Programming Language :: Python :: 3
Classifier: License :: OSI Approved :: MIT License
Classifier: Operating System :: OS Independent
Requires-Python: >=3.6.0
Requires-Dist: dash (>=1.14.0)
Requires-Dist: dash-core-components (>=1.10.2)
Requires-Dist: dash-html-components (>=1.0.3)
Requires-Dist: plotly (>=4.9.0)
Requires-Dist: networkx (>=2.4)
Requires-Dist: matplotlib (>=3.2.1)
Requires-Dist: pandas (>=1.0.3)
Requires-Dist: beautifulsoup4 (>=4.9.1)
Requires-Dist: chart-studio (>=1.1.0)
Requires-Dist: requests (>=2.22.0)
Requires-Dist: Click (>=7.0)
Requires-Dist: lxml (>=4.5.2)
Requires-Dist: scipy (>=1.5.2)
